{
	"statTypes" : [{
			"name" : "Berserker",
			"types" : ["HELMET", "SHOULDERS", "CHEST", "GLOVES", "LEGS", "BOOTS", "BACK", "ACCESSORY", "RING", "AMULET", "ONE_HANDED_WEAPON", "TWO_HANDED_WEAPON", "SHIELD"],
			"stats" : ["POWER", "PRECISION", "FEROCITY"]
		}, {
			"name" : "Soldier",
			"types" : ["HELMET", "SHOULDERS", "CHEST", "GLOVES", "LEGS", "BOOTS", "BACK", "ACCESSORY", "RING", "AMULET", "ONE_HANDED_WEAPON", "TWO_HANDED_WEAPON", "SHIELD"],
			"stats" : ["POWER", "TOUGHNESS", "VITALITY"]
		}, {
			"name" : "Valkyrie",
			"types" : ["HELMET", "SHOULDERS", "CHEST", "GLOVES", "LEGS", "BOOTS", "ONE_HANDED_WEAPON", "TWO_HANDED_WEAPON", "SHIELD"],
			"stats" : ["POWER", "VITALITY", "FEROCITY"]
		}, {
			"name" : "Asssassin",
			"types" : ["HELMET", "SHOULDERS", "CHEST", "GLOVES", "LEGS", "BOOTS", "ONE_HANDED_WEAPON", "TWO_HANDED_WEAPON", "SHIELD"],
			"stats" : ["PRECISION", "POWER", "FEROCITY"]
		}, {
			"name" : "Rampager",
			"types" : ["HELMET", "SHOULDERS", "CHEST", "GLOVES", "LEGS", "BOOTS", "BACK", "ACCESSORY", "RING", "AMULET", "ONE_HANDED_WEAPON", "TWO_HANDED_WEAPON", "SHIELD"],
			"stats" : ["PRECISION", "POWER", "CONDITION_DAMAGE"]
		}, {
			"name" : "Cavalier",
			"types" : ["HELMET", "SHOULDERS", "CHEST", "GLOVES", "LEGS", "BOOTS", "BACK", "ACCESSORY", "RING", "AMULET", "ONE_HANDED_WEAPON", "TWO_HANDED_WEAPON", "SHIELD"],
			"stats" : ["TOUGHNESS", "POWER", "FEROCITY"]
		}, {
			"name" : "Knight",
			"types" : ["HELMET", "SHOULDERS", "CHEST", "GLOVES", "LEGS", "BOOTS", "BACK", "ACCESSORY", "RING", "AMULET", "ONE_HANDED_WEAPON", "TWO_HANDED_WEAPON", "SHIELD"],
			"stats" : ["TOUGHNESS", "POWER", "PRECISION"]
		}, {
			"name" : "Settler",
			"types" : ["HELMET", "SHOULDERS", "CHEST", "GLOVES", "LEGS", "BOOTS", "ONE_HANDED_WEAPON", "TWO_HANDED_WEAPON", "SHIELD"],
			"stats" : ["TOUGHNESS", "CONDITION_DAMAGE", "HEALING_POWER"]
		}, {
			"name" : "Sentinel",
			"types" : ["HELMET", "SHOULDERS", "CHEST", "GLOVES", "LEGS", "BOOTS", "ONE_HANDED_WEAPON", "TWO_HANDED_WEAPON", "SHIELD"],
			"stats" : ["VITALITY", "POWER", "TOUGHNESS"]
		}, {
			"name" : "Shaman",
			"types" : ["HELMET", "SHOULDERS", "CHEST", "GLOVES", "LEGS", "BOOTS", "ONE_HANDED_WEAPON", "TWO_HANDED_WEAPON", "SHIELD"],
			"stats" : ["VITALITY", "HEALING_POWER", "CONDITION_DAMAGE"]
		}, {
			"name" : "Carrion",
			"types" : ["HELMET", "SHOULDERS", "CHEST", "GLOVES", "LEGS", "BOOTS", "ONE_HANDED_WEAPON", "TWO_HANDED_WEAPON", "SHIELD"],
			"stats" : ["CONDITION_DAMAGE", "POWER", "VITALITY"]
		}, {
			"name" : "Dire",
			"types" : ["HELMET", "SHOULDERS", "CHEST", "GLOVES", "LEGS", "BOOTS", "ONE_HANDED_WEAPON", "TWO_HANDED_WEAPON", "SHIELD"],
			"stats" : ["CONDITION_DAMAGE", "TOUGHNESS", "VITALITY"]
		}, {
			"name" : "Rabid",
			"types" : ["HELMET", "SHOULDERS", "CHEST", "GLOVES", "LEGS", "BOOTS", "BACK", "ACCESSORY", "RING", "AMULET", "ONE_HANDED_WEAPON", "TWO_HANDED_WEAPON", "SHIELD"],
			"stats" : ["CONDITION_DAMAGE", "TOUGHNESS", "PRECISION"]
		}, {
			"name" : "Apothecary",
			"types" : ["HELMET", "SHOULDERS", "CHEST", "GLOVES", "LEGS", "BOOTS", "BACK", "ACCESSORY", "RING", "AMULET", "ONE_HANDED_WEAPON", "TWO_HANDED_WEAPON", "SHIELD"],
			"stats" : ["HEALING_POWER", "CONDITION_DAMAGE", "TOUGHNESS"]
		}, {
			"name" : "Cleric",
			"types" : ["HELMET", "SHOULDERS", "CHEST", "GLOVES", "LEGS", "BOOTS", "BACK", "ACCESSORY", "RING", "AMULET", "ONE_HANDED_WEAPON", "TWO_HANDED_WEAPON", "SHIELD"],
			"stats" : ["HEALING_POWER", "POWER", "TOUGHNESS"]
		}, {
			"name" : "Magi",
			"types" : ["HELMET", "SHOULDERS", "CHEST", "GLOVES", "LEGS", "BOOTS", "ONE_HANDED_WEAPON", "TWO_HANDED_WEAPON", "SHIELD"],
			"stats" : ["HEALING_POWER", "VITALITY", "PRECISION"]
		}, {
			"name" : "Celestial",
			"types" : ["HELMET", "SHOULDERS", "CHEST", "GLOVES", "LEGS", "BOOTS", "BACK", "ACCESSORY", "RING", "AMULET", "ONE_HANDED_WEAPON", "TWO_HANDED_WEAPON", "SHIELD"],
			"stats" : ["POWER", "PRECISION", "TOUGHNESS", "VITALITY", "HEALING_POWER", "FEROCITY", "CONDITION_DAMAGE"]
		}
	]
}
